MANIFEST.in
README.rst
requirements.txt
setup.py
cos_python_sdk_v5_private.egg-info/PKG-INFO
cos_python_sdk_v5_private.egg-info/SOURCES.txt
cos_python_sdk_v5_private.egg-info/dependency_links.txt
cos_python_sdk_v5_private.egg-info/requires.txt
cos_python_sdk_v5_private.egg-info/top_level.txt
qcloud_cos_v5/__init__.py
qcloud_cos_v5/cos_auth.py
qcloud_cos_v5/cos_client.py
qcloud_cos_v5/cos_exception.py
qcloud_cos_v5/cos_threadpool.py
qcloud_cos_v5/streambody.py
qcloud_cos_v5/test.py
qcloud_cos_v5/xml2dict.py